<?xml version="1.0"?>
<opencv_storage>
<imageDescriptor type_id="opencv-matrix">
  <rows>1</rows>
  <cols>1000</cols>
  <dt>f</dt>
  <data>
    0. 0. -1.32392976e-003 0. 0. 0. 0. 0. 0. 0. 0. 0. 0. 0. 0.
    1.79569069e-002 4.64182859e-003 0. 0. 2.41700653e-003 0.
    3.50142946e-003 0. 0. 0. 0. 0. 0. 0. 0. 0. 0. 0. 1.25902435e-002 0.
    0. 0. 0. 0. 1.50770845e-003 -1.39375799e-003 0. 1.97110735e-002 0.
    0. 0. 0. 0. 9.23383422e-003 3.88560165e-003 0. 0. 0. 0. 0. 0. 0. 0.
    0. 0. 0. 0. 0. 0. 0. 0. 7.47882389e-003 0. 0. 0. 0. 0.
    2.77471403e-003 0. 0. 0. 0. 5.52628376e-003 9.09500755e-003 0. 0. 0.
    0. 0. 0. 0. 0. 0. 0. 0. -3.30249895e-004 1.87161770e-002 0.
    1.25026423e-002 0. -3.18321702e-003 0. 0. 5.50161931e-004 0. 0. 0.
    0. 0. 0. 0. 0. 0. 0. 0. 0. 0. 0. 0. 9.65746294e-004 0. 0. 0. 0.
    1.54905794e-002 7.70747010e-003 2.29658443e-003 0. 0. 0. 0. 0. 0. 0.
    0. 0. 0. 0. 0. 0. 6.51562959e-003 0. 0. 0. 0. 0. 0. 0. 0.
    2.35264003e-003 0. 0. 0. 0. 0. 0. 0. 5.54672070e-003 0. 0.
    -1.66793086e-003 -3.31249507e-003 0. 1.44871762e-002 0. 0. 0. 0. 0.
    0. 0. 0. 0. 0. 0. 0. 0. 0. 0. 0. 0. 0. 0. 6.80222316e-003 0. 0. 0.
    0. 0. 0. 0. 0. 2.13697599e-003 0. 0. 0. 0. 0. 0. 0. 0.
    1.24745001e-003 0. 0. 4.15185280e-003 4.69542341e-003 0. 0.
    2.48662587e-002 0. 0. 5.24764508e-003 0. 0. 0. 0. 0. 0.
    3.70187918e-003 0. -4.60192049e-003 0. 0. 0. -6.24382737e-005 0. 0.
    0. 0. 0. 0. 0. 0. 0. -2.81588314e-003 0. 0. 0. 0. 0. 0.
    4.48716432e-003 0. 0. 1.05535705e-002 2.70215925e-002
    1.35709718e-002 0. 0. 0. 0. 1.47440925e-003 1.83561945e-003 0. 0. 0.
    0. 0. 4.27794782e-003 0. -6.88270805e-003 0. 0. 2.47621443e-003
    1.94065471e-003 0. 0. 0. 0. 0. 0. 0. 0. 6.62025996e-003 0. 0. 0.
    -1.98408728e-003 0. 0. 0. 0. 0. 0. 0. 0. 0. 3.17496643e-003
    1.83579291e-003 0. 0. 2.52048462e-003 0. 0. 0. 0. 0. 0.
    -9.32578041e-005 0. 1.86004210e-003 0. 2.44111903e-002 0. 0. 0. 0.
    0. 0. 0. 1.61910348e-003 1.66073756e-003 0. 0. 0. 4.98270663e-003
    -2.84968154e-003 1.70657109e-003 -5.54448413e-003 5.50089963e-003 0.
    0. 0. 0. 0. 0. 0. 3.82234086e-003 0. 0. 0. 0. -9.41199134e-004 0. 0.
    0. 0. 0. 0. 0. 6.91718236e-003 6.97061280e-003 0. 0. 0. 0. 0. 0. 0.
    0. 0. 0. 1.35857407e-002 0. 0. 0. 0. 0. 0. 0. 0. 0. 0. 0. 0. 0.
    1.05593940e-002 0. 0. 6.40957244e-003 0. 0. 5.69255138e-003 0. 0. 0.
    0. 1.65029410e-002 0. 1.86883635e-003 0. 2.74654711e-003 0. 0. 0. 0.
    0. 0. 0. 0. 0. 0. 0. 0. 0. 0. 0. 0. 0. 0. 4.95261559e-003 0. 0. 0.
    0. 0. 0. 0. 0. -2.05510551e-005 0. 0. 0. 0. 0. 0. 0. 0.
    4.52292012e-003 0. 0. 0. 0. 0. 0. 0. 0. 0. 0. 0. 0. 0. 0. 0. 0. 0.
    0. 0. 0. 0. 2.24629324e-003 2.96503608e-003 0. 0. 0. 0.
    3.02295689e-003 0. 0. 0. 0. 0. 0. 0. 0. 3.09073403e-002 0.
    2.09260266e-002 0. 0. 0. 2.79307738e-003 0. 0. 0. 0. 0. 0. 0. 0. 0.
    0. 0. 0. 0. 0. 0. 1.14337821e-002 2.33956985e-003 0. 0. 0. 0. 0. 0.
    0. 1.33256626e-003 0. 0. 0. 2.22630030e-003 0. 0. 0. 0. 0.
    8.91406834e-003 -3.12872115e-003 0. 0. 0. 0. 0. 0. 0. 0. 0.
    2.85321218e-003 0. 0. 0. 9.57822427e-003 7.77487038e-003
    1.33772772e-002 0. 0. 0. 0. 0. 0. 0. 0. 0. 0. 0. 0. 0. 0.
    8.34556669e-003 6.82817074e-003 0. 0. 0. 0. 0. 0. 0. 0. 0. 0. 0.
    -2.20097695e-003 0. -3.09437816e-003 0. 0. 0. 0. 0. 0. 0. 0. 0. 0.
    0. 3.41986958e-003 0. 0. 0. 0. -1.42289628e-003 0. 0. 0. 0.
    3.34757846e-003 -4.87739127e-003 1.10469544e-002 0. 0. 0. 0. 0. 0.
    0. 0. -5.92133123e-003 0. 0. 0. 2.25670286e-004 0. 0. 0. 0. 0. 0. 0.
    0. 0. 2.84082489e-003 -1.92040880e-003 0. 0. -7.76318426e-004
    7.42726726e-003 0. 0. 0. 1.70451924e-002 0. 0. 1.15052343e-003 0. 0.
    0. 0. 0. 0. 0. 0. 0. 0. 0. 0. 0. 0. 0. 0. 0. 0. 0. 0. 0. 0. 0. 0. 0.
    0. 0. 1.93621870e-002 0. 0. 0. 0. 0. 0. 6.21218095e-003
    -1.77321979e-003 0. 1.58662945e-002 0. 0. 0. 0. 0. 0. 0. 0. 0. 0. 0.
    0. 0. 0. 0. 0. 0. 4.10286523e-003 0. 0. 0. 0. 9.37416311e-003 0. 0.
    0. 0. 0. 0. 0. 0. 0. 3.38468258e-003 3.36186890e-003 1.91446248e-004
    0. 0. 0. 0. 0. 0. 0. 0. 0. 0. 0. 0. 0. 0. 0. 0. 0. 0. 0. 0. 0.
    1.96731184e-003 0. 1.31041668e-002 0. 0. 3.00773643e-002 0.
    2.56099436e-003 0. 0. 0. 0. 5.39314793e-003 0. 0. 0. 0. 0. 0. 0. 0.
    0. 0. 7.96821993e-003 0. 1.54126519e-002 0. 0. 0. 0. 0. 0. 0. 0. 0.
    0. 1.09798778e-002 0. 0. 0. 0. 0. 0. 0. 4.41089086e-003 0. 0. 0. 0.
    0. 4.95567732e-003 0. 0. 0. 8.09575373e-004 0. 1.39839724e-002 0. 0.
    0. 0. 0. 0. 0. 0. -6.84845541e-003 0. 0. -3.49156256e-003 0. 0. 0.
    0. 0. 0. 2.68258732e-002 0. 0. 0. -3.45382490e-003 0. 0. 0. 0.
    3.52322031e-003 0. 0. 0. 0. 0. 0. 0. 0. 0. 0. -2.50900979e-003 0. 0.
    9.16980673e-003 0. 0. 2.15919386e-003 0. -3.65731446e-003 0. 0. 0.
    0. -2.02884851e-003 6.47582067e-003 0. 0. 0. 0. 0. 0.
    4.33227932e-003 0. 0. 0. 0. 7.06229080e-003 0. 0. 0. 1.49651282e-002
    1.85936522e-002 0. 0. 0. 0. 0. 1.61107741e-002 0. 0. 3.68402735e-003
    0. 0. 0. 0. -4.86793788e-003 1.47518246e-002 0. 0. 0. 0. 0. 0. 0. 0.
    0. 0. 0. 0. 0. 0. 2.26084702e-003 2.74128118e-003 0. 0.
    4.06232337e-003 0. 3.77076608e-003 0. 0. 0. -9.64898337e-003 0.
    6.63206866e-003 0. 8.40181950e-003 0. 0. 0. 0. 0. 0. 0. 0.
    2.38139778e-002 0. 0. 0. 8.33075866e-003 0. 0. 0. 1.63380280e-002 0.
    0. 0. 0. 0. 0. 1.30335940e-002 2.66545662e-003 0. 8.98295455e-003
    4.73965006e-003 1.71875544e-002 0. 0. 0. 0. 0. 0. 0. 0. 0. 0. 0. 0.
    0. 0. 0. 0. 0. 0. 0. 0. 3.85137228e-003 0. 1.54151837e-003 0.
    3.04424018e-003 0. 0. 0. 0. 0. 0. 0. 0. 4.91599133e-003 0.
    2.19479809e-003 0. 0. 0. 0. 0. 0. 0. 0. 1.11627602e-003 0. 0. 0.
    3.55608203e-003 0. 4.42448957e-003 0. 6.70869416e-003 0. 0. 0. 0. 0.
    0. 0. 0. 0. 0. 8.67969764e-004 0. 0. 0. 0. 0. 0. 0. 0.
    1.89081777e-003 0. 0. 0. 0. 5.07070217e-003 0. 0. 0. 0. 0. 0. 0. 0.
    0. 0. 0. 0. 0. 0. 0. 0. 0. 0. 0. 0. 0. 0. 0. 0. 0. 0.
    2.59980536e-003 0. 0. 0.</data></imageDescriptor>
</opencv_storage>
